dtachwrap/proc.py
dtachwrap/cli.py
dtachwrap/state.py
dtachwrap/dtachbin.py
dtachwrap/log_wrapper.py
dtachwrap/__init__.py
dtachwrap/_vendor/NOTICE
dtachwrap/_vendor/__init__.py
dtachwrap/_vendor/licenses/DTACH_COPYING
dtachwrap/_vendor/bin/dtach
dtachwrap/_vendor/src/dtach/attach.c
dtachwrap/_vendor/src/dtach/dtach.h
dtachwrap/_vendor/src/dtach/configure.ac
dtachwrap/_vendor/src/dtach/config.h.in
dtachwrap/_vendor/src/dtach/master.c
dtachwrap/_vendor/src/dtach/config.status
dtachwrap/_vendor/src/dtach/dtach.1
dtachwrap/_vendor/src/dtach/configure
dtachwrap/_vendor/src/dtach/config.h
dtachwrap/_vendor/src/dtach/COPYING
dtachwrap/_vendor/src/dtach/dtach.spec
dtachwrap/_vendor/src/dtach/Makefile.in
dtachwrap/_vendor/src/dtach/config.log
dtachwrap/_vendor/src/dtach/main.c
dtachwrap/_vendor/src/dtach/README
dtachwrap/_vendor/src/dtach/Makefile
dtachwrap-0.1.0.post1.dist-info/WHEEL
dtachwrap-0.1.0.post1.dist-info/entry_points.txt
dtachwrap-0.1.0.post1.dist-info/top_level.txt
dtachwrap-0.1.0.post1.dist-info/METADATA
dtachwrap-0.1.0.post1.dist-info/RECORD
