Metadata-Version: 2.4
Name: dtachwrap
Version: 0.1.0.post1
Summary: Python wrapper for dtach with built-in binary management
Project-URL: Homepage, https://github.com/HarborYuan/dtachwrap
Classifier: Programming Language :: Python :: 3
Classifier: Operating System :: POSIX :: Linux
Classifier: License :: OSI Approved :: MIT License
Requires-Python: >=3.10
Requires-Dist: typer>=0.9.0
